demilich/__init__.py
demilich/__main__.py
demilich/cli.py
demilich/data/demilich.schema.json
demilich/data/pb2024.toml
demilich/examples/dev.py
demilich/examples/play_booster_2024.py
demilich/output.py
demilich/reader.py
demilich/skeleton.py
demilich-1.2.1.dist-info/LICENSE
demilich-1.2.1.dist-info/METADATA
demilich-1.2.1.dist-info/WHEEL
demilich-1.2.1.dist-info/entry_points.txt
demilich-1.2.1.dist-info/RECORD
