Metadata-Version: 2.1
Name: demilich
Version: 1.2.1
Summary: Demilich, the MTG skeleton wizard
Home-page: https://github.com/vtbassmatt/demilich
Keywords: game,tcg,mtg,magic
Author: Matt Cooper
Author-email: vtbassmatt@gmail.com
Requires-Python: >=3.12,<4.0
Classifier: Programming Language :: Python :: 3
Classifier: Programming Language :: Python :: 3.12
Requires-Dist: typer (>=0.15.1,<0.16.0)
Project-URL: Bug Tracker, https://github.com/vtbassmatt/demilich/issues
Project-URL: Documentation, https://github.com/vtbassmatt/demilich
Project-URL: Repository, https://github.com/vtbassmatt/demilich
